katsuyo_text/__init__.py
katsuyo_text/katsuyo.py
katsuyo_text/katsuyo_text.py
katsuyo_text/katsuyo_text_detector.py
katsuyo_text/katsuyo_text_helper.py
katsuyo_text/sentence_converter.py
katsuyo_text/spacy_katsuyo_text_detector.py
katsuyo_text/spacy_sentence_converter.py
katsuyo_text-0.1.2.dist-info/LICENSE
katsuyo_text-0.1.2.dist-info/WHEEL
katsuyo_text-0.1.2.dist-info/METADATA
katsuyo_text-0.1.2.dist-info/RECORD
