Metadata-Version: 2.1
Name: katsuyo-text
Version: 0.1.2
Summary: A Japanese conjugation form converter
License: MIT
Author: Sadahiro YOSHIKAWA
Requires-Python: >=3.10,<4.0
Classifier: License :: OSI Approved :: MIT License
Classifier: Programming Language :: Python :: 3
Classifier: Programming Language :: Python :: 3.10
Requires-Dist: spacy (>=3.4.1,<4.0.0)
